flex/__init__.py
flex/account_client.py
flex/account_property_client.py
flex/flex_api_client.py
flex/flex_objects.py
flex_sdk-0.8.dist-info/METADATA
flex_sdk-0.8.dist-info/WHEEL
flex_sdk-0.8.dist-info/top_level.txt
flex_sdk-0.8.dist-info/RECORD
