Metadata-Version: 2.4
Name: flex-sdk
Version: 0.8
Summary: Python SDK for Flex API
Requires-Python: >=3.7
Requires-Dist: requests
